{
  "name": "Capteur d'ouverture",
  "ref" : "TS203",
  "type": "Ouverture",
  "buylink" : "",
  "remark" : "",
  "commands": [
    {
      "name": "Ouverture",
      "type": "info",
      "subtype": "binary",
      "isVisible": 1,
      "isHistorized": 0,
      "logicalId": "1::1280::cmd::1",
      "generic_type": "OPENING",
      "configuration": {
        "repeatEventManagement": "always"
      },
      "template" : {
        "dashboard" : "door",
        "mobile" : "door"
      },
      "template" : {
        "dashboard" : "window",
        "mobile" : "window"
      }
    }
  ]
}
