{
  "name": "MOES - Thermostat intelligent",
  "ref" : "TS0601",
  "buylink" : "",
  "commands": [
    {
      "name": "Température",
      "type": "info",
      "subtype": "numeric",
      "isVisible": 1,
      "isHistorized": 1,
      "unite" : "°C",
      "logicalId": "temperature",
      "generic_type" : "THERMOSTAT_TEMPERATURE",
      "configuration" : {
        "calculValueOffset":"#value# / 10"
      }
    },
    {
      "name": "Consigne",
      "type": "info",
      "subtype": "numeric",
      "isVisible": 0,
      "isHistorized": 0,
      "unite" : "°C",
      "logicalId": "target",
      "generic_type" : "THERMOSTAT_SETPOINT",
      "configuration" : {
        "calculValueOffset":"#value#"
      }
    },
    {
      "name": "Mode",
      "type": "info",
      "subtype": "string",
      "isVisible": 1,
      "isHistorized": 0,
      "generic_type" : "THERMOSTAT_STATE_NAME",
      "logicalId": "mode"
    },
    {
      "name": "Ventilation",
      "type": "info",
      "subtype": "numeric",
      "isVisible": 1,
      "isHistorized": 0,
      "logicalId": "ventilation"
    }
  ]
}
