{
  "apt" : {
    "python3" : {},
    "python3-pip" : {}
  },
  "pip3" : {
    "pyudev" : {},
    "requests" : {},
    "setuptools" : {},
    "wheel" : {},
    "pyserial" : {},
    "tornado" : {},
    "zigpy" : {"reinstall" : true},
    "zha-quirks" : {"reinstall" : true},
    "zigpy-znp" : {"reinstall" : true},
    "zigpy-xbee" : {"reinstall" : true},
    "zigpy-deconz" : {"reinstall" : true},
    "zigpy-zigate" : {"reinstall" : true},
    "bellows" : {"reinstall" : true}
  },
  "post-install" : {
    "script" : "plugins/zigbee/resources/post-install.sh"
  }
}