{
  "name": "Sonoff Température/humidité",
  "buylink" : "https://www.domadoo.fr/fr/peripheriques/5260-sonoff-capteur-de-temperature-et-d-humidite-zigbee-30.html",
  "commands": [
    {
      "name": "Humidité",
      "type": "info",
      "subtype": "numeric",
      "isVisible": 1,
      "isHistorized": 0,
      "logicalId": "1::1029::0",
      "unite" : "%",
      "configuration" : {
        "calculValueOffset":"#value# / 100"
      }
    },
    {
      "name": "Température",
      "type": "info",
      "subtype": "numeric",
      "isVisible": 1,
      "isHistorized": 0,
      "logicalId": "1::1026::0",
      "unite" : "°C",
      "configuration" : {
        "calculValueOffset":"#value# / 100"
      }
    }
  ]
}
